GPTCLI/__init__.py
GPTCLI/__main__.py
GPTCLI/addons.py
GPTCLI/bard.py
GPTCLI/emage.py
GPTCLI/gptcli.py
GPTCLI/helper.py
GPTCLI/image.py
chatgpt4_cli-1.5.9.dist-info/LICENSE
chatgpt4_cli-1.5.9.dist-info/METADATA
chatgpt4_cli-1.5.9.dist-info/WHEEL
chatgpt4_cli-1.5.9.dist-info/entry_points.txt
chatgpt4_cli-1.5.9.dist-info/top_level.txt
chatgpt4_cli-1.5.9.dist-info/RECORD
