Metadata-Version: 2.1
Name: chatgpt4-cli
Version: 1.5.9
Summary: Interact with ChatGPT and Bard at the terminal.
Home-page: https://github.com/Simatwa/gpt-cli
Author: Smartwa Caleb
Author-email: smartwacaleb@gmail.com
Maintainer: Smartwa Caleb
License: MIT
Project-URL: Bug Report, https://github.com/Simatwa/gpt-cli/issues/new
Classifier: License :: OSI Approved :: MIT License
Classifier: Development Status :: 4 - Beta
Classifier: Intended Audience :: Developers
Classifier: Natural Language :: English
Classifier: License :: Free For Home Use
Classifier: Topic :: Home Automation
Classifier: Intended Audience :: Customer Service
Classifier: Programming Language :: Python
Classifier: Topic :: Software Development :: Libraries :: Python Modules
Classifier: Programming Language :: Python :: 3 :: Only
Classifier: Programming Language :: Python :: 3.8
Classifier: Programming Language :: Python :: 3.9
Classifier: Programming Language :: Python :: 3.10
Classifier: Programming Language :: Python :: 3.11
License-File: LICENSE
Requires-Dist: numpy >=1.23.4
Requires-Dist: colorama >=0.4.6
Requires-Dist: openai >=0.26.4
Requires-Dist: revChatGPT ==4.0.6
Requires-Dist: appdirs >=1.4.4
Requires-Dist: requests >=2.28.2
Requires-Dist: tabulate >=0.9.0
Requires-Dist: GoogleBard ==1.4.0
Requires-Dist: fpdf ==1.7.2
